skypilot_provider/__init__.py
skypilot_provider/example_dags/sky_airflow_example.py
skypilot_provider/hooks/__init__.py
skypilot_provider/hooks/sky_ssh.py
skypilot_provider/operators/__init__.py
skypilot_provider/operators/core_function.py
skypilot_provider/operators/rsync.py
skypilot_provider/operators/ssh.py
skypilot_provider/skycore/__init__.py
skypilot_provider/skycore/sky_bash_cmd.py
skypilot_provider/skycore/sky_core.py
skypilot_provider/skycore/sky_log.py
airflow_provider_skypilot-0.1.3.dist-info/LICENSE
airflow_provider_skypilot-0.1.3.dist-info/METADATA
airflow_provider_skypilot-0.1.3.dist-info/WHEEL
airflow_provider_skypilot-0.1.3.dist-info/entry_points.txt
airflow_provider_skypilot-0.1.3.dist-info/top_level.txt
airflow_provider_skypilot-0.1.3.dist-info/RECORD
