Metadata-Version: 2.1
Name: airflow-provider-skypilot
Version: 0.1.3
Summary: A sample Apache Airflow provider package built by Astronomer.
Author-email: Suk-hoon Jung <pete@astronomer.io>
License: Apache License 2.0
Project-URL: Homepage, https://astronomer.io
Project-URL: Source, https://github.com/astronomer/airflow-provider-sample/
Classifier: Framework :: Apache Airflow
Classifier: Framework :: Apache Airflow :: Provider
Classifier: Operating System :: POSIX :: Linux
Classifier: Programming Language :: Python :: 3.7
Classifier: Programming Language :: Python :: 3.8
Classifier: Programming Language :: Python :: 3.9
Classifier: Programming Language :: Python :: 3.10
Requires-Python: >=3.7
License-File: LICENSE
Requires-Dist: apache-airflow >=2.4
Requires-Dist: skypilot >=0.4.1
Requires-Dist: paramiko >=3.3.1
